bin2png.py
bin2png-2.1.dist-info/LICENSE
bin2png-2.1.dist-info/METADATA
bin2png-2.1.dist-info/WHEEL
bin2png-2.1.dist-info/entry_points.txt
bin2png-2.1.dist-info/top_level.txt
bin2png-2.1.dist-info/RECORD
